1,3c1,3
< Compiled from "Test.java"
< public class Test {
<   public Test();
---
> Compiled from "Test2.java"
> public class Test2 {
>   public Test2();
11,32c11,30
<        0: ldc           #2                  // String 
<        2: astore_1      
<        3: iconst_0      
<        4: istore_2      
<        5: iload_2       
<        6: sipush        10000
<        9: if_icmpge     37
<       12: new           #3                  // class java/lang/StringBuilder
<       15: dup           
<       16: invokespecial #4                  // Method java/lang/StringBuilder."<init>":()V
<       19: aload_1       
<       20: invokevirtual #5                  // Method java/lang/StringBuilder.append:(Ljava/lang/String;)Ljava/lang/StringBuilder;
<       23: iload_2       
<       24: invokevirtual #6                  // Method java/lang/StringBuilder.append:(I)Ljava/lang/StringBuilder;
<       27: invokevirtual #7                  // Method java/lang/StringBuilder.toString:()Ljava/lang/String;
<       30: astore_1      
<       31: iinc          2, 1
<       34: goto          5
<       37: getstatic     #8                  // Field java/lang/System.out:Ljava/io/PrintStream;
<       40: aload_1       
<       41: invokevirtual #9                  // Method java/io/PrintStream.println:(Ljava/lang/String;)V
<       44: return        
---
>        0: new           #2                  // class java/lang/StringBuilder
>        3: dup           
>        4: invokespecial #3                  // Method java/lang/StringBuilder."<init>":()V
>        7: astore_1      
>        8: iconst_0      
>        9: istore_2      
>       10: iload_2       
>       11: sipush        10000
>       14: if_icmpge     29
>       17: aload_1       
>       18: iload_2       
>       19: invokevirtual #4                  // Method java/lang/StringBuilder.append:(I)Ljava/lang/StringBuilder;
>       22: pop           
>       23: iinc          2, 1
>       26: goto          10
>       29: getstatic     #5                  // Field java/lang/System.out:Ljava/io/PrintStream;
>       32: aload_1       
>       33: invokevirtual #6                  // Method java/lang/StringBuilder.toString:()Ljava/lang/String;
>       36: invokevirtual #7                  // Method java/io/PrintStream.println:(Ljava/lang/String;)V
>       39: return        
